{"tweets": [{"created_at": "Sun Nov 21 14:23:47 +0000 2021", "id": 1100843, "full_text": "\u0627\u0644\u0644\u0647\u0645 \u0623\u062c\u0631\u0646\u0627 \u0641\u064a \u0645\u0635\u064a\u0628\u062a\u0646\u0627 \u0648\u0627\u062e\u0644\u0641 \u0644\u0646\u0627 \u062e\u064a\u0631\u0627\n#\u062d\u062a\u0645\u0627 \u0633\u0646\u0646\u0647\u0636 https://t.co/85gAHaCz85", "truncated": false, "display_text_range": [0, 49], "entities": {"hashtags": [{"text": "\u062d\u062a\u0645\u0627", "indices": [38, 43]}], "symbols": [], "user_mentions": [], "urls": [], "media": [{"id": 1462426516311220229, "id_str": "1462426516311220229", "indices": [50, 73], "media_url": "http://pbs.twimg.com/media/FEuVKxbXoAUAw94.jpg", "media_url_https": "https://pbs.twimg.com/media/FEuVKxbXoAUAw94.jpg", "url": "https://t.co/85gAHaCz85", "display_url": "pic.twitter.com/85gAHaCz85", "expanded_url": "https://twitter.com/elshenawi4/status/1462426519087820808/photo/1", "type": "photo", "sizes": {"small": {"w": 582, "h": 680, "resize": "fit"}, "thumb": {"w": 150, "h": 150, "resize": "crop"}, "large": {"w": 1080, "h": 1262, "resize": "fit"}, "medium": {"w": 1027, "h": 1200, "resize": "fit"}}}]}, "extended_entities": {"media": [{"id": 1462426516311220229, "id_str": "1462426516311220229", "indices": [50, 73], "media_url": "http://pbs.twimg.com/media/FEuVKxbXoAUAw94.jpg", "media_url_https": "https://pbs.twimg.com/media/FEuVKxbXoAUAw94.jpg", "url": "https://t.co/85gAHaCz85", "display_url": "pic.twitter.com/85gAHaCz85", "expanded_url": "https://twitter.com/elshenawi4/status/1462426519087820808/photo/1", "type": "photo", "sizes": {"small": {"w": 582, "h": 680, "resize": "fit"}, "thumb": {"w": 150, "h": 150, "resize": "crop"}, "large": {"w": 1080, "h": 1262, "resize": "fit"}, "medium": {"w": 1027, "h": 1200, "resize": "fit"}}}]}, "source": "<a href=\"http://twitter.com/download/android\" rel=\"nofollow\">Twitter for Android</a>", "in_reply_to_status_id": 100001, "geo": null, "coordinates": null, "place": null, "contributors": null, "is_quote_status": false, "retweet_count": 0, "favorite_count": 1, "favorited": false, "retweeted": false, "possibly_sensitive": false, "lang": "ar"}, {"created_at": "Sun Nov 21 06:57:57 +0000 2021", "id": 1100844, "full_text": "#\u0644\u0627 \u062a\u0641\u0627\u0648\u0636 \u0645\u0639 \u0639\u0635\u0627\u0628\u0647 \u0627\u0644\u062e\u0645\u0633\u0647 \n#\u0644\u0627 \u062a\u0643\u0648\u0646 \u062a\u0648\u0645 \u0647\u062c\u0648 \n#\u0644\u0646 \u0646\u0646\u062a\u0638\u0631 \u0628\u064a\u0627\u0646 https://t.co/ig2HVXNEVk", "truncated": false, "display_text_range": [0, 59], "entities": {"hashtags": [{"text": "\u0644\u0627", "indices": [0, 3]}, {"text": "\u0644\u0627", "indices": [27, 30]}, {"text": "\u0644\u0646", "indices": [45, 48]}], "symbols": [], "user_mentions": [], "urls": [], "media": [{"id": 1462314313230729219, "id_str": "1462314313230729219", "indices": [60, 83], "media_url": "http://pbs.twimg.com/media/FEsvHsYWQAMaPNT.jpg", "media_url_https": "https://pbs.twimg.com/media/FEsvHsYWQAMaPNT.jpg", "url": "https://t.co/ig2HVXNEVk", "display_url": "pic.twitter.com/ig2HVXNEVk", "expanded_url": "https://twitter.com/elshenawi4/status/1462314320516292619/photo/1", "type": "photo", "sizes": {"thumb": {"w": 150, "h": 150, "resize": "crop"}, "large": {"w": 1080, "h": 1080, "resize": "fit"}, "medium": {"w": 1080, "h": 1080, "resize": "fit"}, "small": {"w": 680, "h": 680, "resize": "fit"}}}]}, "extended_entities": {"media": [{"id": 1462314313230729219, "id_str": "1462314313230729219", "indices": [60, 83], "media_url": "http://pbs.twimg.com/media/FEsvHsYWQAMaPNT.jpg", "media_url_https": "https://pbs.twimg.com/media/FEsvHsYWQAMaPNT.jpg", "url": "https://t.co/ig2HVXNEVk", "display_url": "pic.twitter.com/ig2HVXNEVk", "expanded_url": "https://twitter.com/elshenawi4/status/1462314320516292619/photo/1", "type": "photo", "sizes": {"thumb": {"w": 150, "h": 150, "resize": "crop"}, "large": {"w": 1080, "h": 1080, "resize": "fit"}, "medium": {"w": 1080, "h": 1080, "resize": "fit"}, "small": {"w": 680, "h": 680, "resize": "fit"}}}]}, "source": "<a href=\"http://twitter.com/download/android\" rel=\"nofollow\">Twitter for Android</a>", "in_reply_to_status_id": 100001, "geo": null, "coordinates": null, "place": null, "contributors": null, "is_quote_status": false, "retweet_count": 0, "favorite_count": 0, "favorited": false, "retweeted": false, "possibly_sensitive": false, "lang": "ar"}, {"created_at": "Mon Feb 22 11:17:27 +0000 2021", "id": 1100845, "full_text": "\u0627\u0644\u062a\u0639\u0648\u064a\u0645 \u0644\u0646 \u064a\u062c\u062f\u064a \u0623\u0646 \u0644\u0645 \u062a\u0642\u0627\u0645 \u0623\u0631\u0643\u0627\u0646 \u0627\u0644\u0639\u062f\u0627\u0644\u0647\n\u0648\u0644\u0646 \u062a\u0642\u0648\u0645 \u0623\u0631\u0643\u0627\u0646 \u0627\u0644\u0639\u062f\u0627\u0644\u0647 \u0644\u0623\u0646 \u0647\u0624\u0644\u0627\u0621 \u0627\u0644\u0648\u062c\u0648\u0647 \u062a\u064f\u0645\u0633\u0643\n \u0628\u062a\u0644\u0627\u0628\u064a\u0628 \u0627\u0644\u0633\u064f\u0644\u0637\u0629 \u0648\u0645\u0631\u0639\u0648\u0628\u064a\u0646 \u0645\u0646 \u0627\u0644\u0645\u062c\u0647\u0648\u0644\n\u0648\u0644\u0646 \u064a\u062c\u062f\u064a \u0646\u0639\u062a \u0627\u0644\u0646\u0627\u0633 \u0628\u0627\u0644\u0643\u0648\u0632\u0646\u0647 \u0648 \u0627\u0644\u0634\u064a\u0648\u0639\u064a\u0629 https://t.co/5NRtHEUk0s", "truncated": false, "display_text_range": [0, 162], "entities": {"hashtags": [], "symbols": [], "user_mentions": [], "urls": [], "media": [{"id": 1363810103468687360, "id_str": "1363810103468687360", "indices": [163, 186], "media_url": "http://pbs.twimg.com/media/Eu06EDZXAAAcZKw.jpg", "media_url_https": "https://pbs.twimg.com/media/Eu06EDZXAAAcZKw.jpg", "url": "https://t.co/5NRtHEUk0s", "display_url": "pic.twitter.com/5NRtHEUk0s", "expanded_url": "https://twitter.com/elshenawi4/status/1363810127887884288/photo/1", "type": "photo", "sizes": {"thumb": {"w": 150, "h": 150, "resize": "crop"}, "medium": {"w": 1024, "h": 1024, "resize": "fit"}, "large": {"w": 1024, "h": 1024, "resize": "fit"}, "small": {"w": 680, "h": 680, "resize": "fit"}}}]}, "extended_entities": {"media": [{"id": 1363810103468687360, "id_str": "1363810103468687360", "indices": [163, 186], "media_url": "http://pbs.twimg.com/media/Eu06EDZXAAAcZKw.jpg", "media_url_https": "https://pbs.twimg.com/media/Eu06EDZXAAAcZKw.jpg", "url": "https://t.co/5NRtHEUk0s", "display_url": "pic.twitter.com/5NRtHEUk0s", "expanded_url": "https://twitter.com/elshenawi4/status/1363810127887884288/photo/1", "type": "photo", "sizes": {"thumb": {"w": 150, "h": 150, "resize": "crop"}, "medium": {"w": 1024, "h": 1024, "resize": "fit"}, "large": {"w": 1024, "h": 1024, "resize": "fit"}, "small": {"w": 680, "h": 680, "resize": "fit"}}}, {"id": 1363810113807667203, "id_str": "1363810113807667203", "indices": [163, 186], "media_url": "http://pbs.twimg.com/media/Eu06Ep6XUAMUxLH.jpg", "media_url_https": "https://pbs.twimg.com/media/Eu06Ep6XUAMUxLH.jpg", "url": "https://t.co/5NRtHEUk0s", "display_url": "pic.twitter.com/5NRtHEUk0s", "expanded_url": "https://twitter.com/elshenawi4/status/1363810127887884288/photo/1", "type": "photo", "sizes": {"large": {"w": 960, "h": 640, "resize": "fit"}, "thumb": {"w": 150, "h": 150, "resize": "crop"}, "small": {"w": 680, "h": 453, "resize": "fit"}, "medium": {"w": 960, "h": 640, "resize": "fit"}}}, {"id": 1363810116492029955, "id_str": "1363810116492029955", "indices": [163, 186], "media_url": "http://pbs.twimg.com/media/Eu06Ez6XcAMwTX7.jpg", "media_url_https": "https://pbs.twimg.com/media/Eu06Ez6XcAMwTX7.jpg", "url": "https://t.co/5NRtHEUk0s", "display_url": "pic.twitter.com/5NRtHEUk0s", "expanded_url": "https://twitter.com/elshenawi4/status/1363810127887884288/photo/1", "type": "photo", "sizes": {"thumb": {"w": 150, "h": 150, "resize": "crop"}, "large": {"w": 1080, "h": 563, "resize": "fit"}, "medium": {"w": 1080, "h": 563, "resize": "fit"}, "small": {"w": 680, "h": 354, "resize": "fit"}}}, {"id": 1363810125211987968, "id_str": "1363810125211987968", "indices": [163, 186], "media_url": "http://pbs.twimg.com/media/Eu06FUZXcAA09l5.jpg", "media_url_https": "https://pbs.twimg.com/media/Eu06FUZXcAA09l5.jpg", "url": "https://t.co/5NRtHEUk0s", "display_url": "pic.twitter.com/5NRtHEUk0s", "expanded_url": "https://twitter.com/elshenawi4/status/1363810127887884288/photo/1", "type": "photo", "sizes": {"thumb": {"w": 150, "h": 150, "resize": "crop"}, "small": {"w": 680, "h": 480, "resize": "fit"}, "medium": {"w": 960, "h": 677, "resize": "fit"}, "large": {"w": 960, "h": 677, "resize": "fit"}}}]}, "source": "<a href=\"http://twitter.com/download/android\" rel=\"nofollow\">Twitter for Android</a>", "in_reply_to_status_id": 100001, "geo": null, "coordinates": null, "place": null, "contributors": null, "is_quote_status": false, "retweet_count": 0, "favorite_count": 0, "favorited": false, "retweeted": false, "possibly_sensitive": false, "lang": "ar"}, {"created_at": "Sat Jan 09 18:35:57 +0000 2021", "id": 1100846, "full_text": "\u0627\u0644\u0625\u0633\u0644\u0627\u0645 \u0634\u0645\u0633 \u0644\u0627 \u062a\u063a\u064a\u0628 \u0625\u0646 \u0628\u0627\u0631\u062d\u062a \u0631\u0624\u0648\u0633 \u0642\u0648\u0645 \u0627\u0646\u0627\u0631\u062a \u0639\u0646\u062f \u0622\u062e\u0631\u064a\u0646\nIslam is a sun that does not disappear if the heads of people are illuminated by others", "truncated": false, "display_text_range": [0, 141], "entities": {"hashtags": [], "symbols": [], "user_mentions": [], "urls": []}, "source": "<a href=\"http://twitter.com/download/android\" rel=\"nofollow\">Twitter for Android</a>", "in_reply_to_status_id": 100001, "geo": null, "coordinates": null, "place": null, "contributors": null, "is_quote_status": false, "retweet_count": 0, "favorite_count": 1, "favorited": false, "retweeted": false, "lang": "ca"}, {"created_at": "Mon Dec 28 06:24:31 +0000 2020", "id": 1100847, "full_text": "\u0644\u0644\u0639\u0645\u064a\u0642\u064a\u0646 \u062c\u062f\u0627\n\u0627\u0644\u0643\u0648\u0632 \u0627\u0646 \u0644\u0645 \u064a\u062c\u062f \u0645\u0627 \u064a\u0627\u0643\u0644\u0647 \u0627\u0643\u0644 \u0646\u0641\u0633\u0647 https://t.co/rN89IXZ4MB", "truncated": false, "display_text_range": [0, 46], "entities": {"hashtags": [], "symbols": [], "user_mentions": [], "urls": [], "media": [{"id": 1343442686402043905, "id_str": "1343442686402043905", "indices": [47, 70], "media_url": "http://pbs.twimg.com/media/EqTeAWMXIAE5ljl.jpg", "media_url_https": "https://pbs.twimg.com/media/EqTeAWMXIAE5ljl.jpg", "url": "https://t.co/rN89IXZ4MB", "display_url": "pic.twitter.com/rN89IXZ4MB", "expanded_url": "https://twitter.com/elshenawi4/status/1343442688939585536/photo/1", "type": "photo", "sizes": {"thumb": {"w": 150, "h": 150, "resize": "crop"}, "small": {"w": 384, "h": 200, "resize": "fit"}, "medium": {"w": 384, "h": 200, "resize": "fit"}, "large": {"w": 384, "h": 200, "resize": "fit"}}}]}, "extended_entities": {"media": [{"id": 1343442686402043905, "id_str": "1343442686402043905", "indices": [47, 70], "media_url": "http://pbs.twimg.com/media/EqTeAWMXIAE5ljl.jpg", "media_url_https": "https://pbs.twimg.com/media/EqTeAWMXIAE5ljl.jpg", "url": "https://t.co/rN89IXZ4MB", "display_url": "pic.twitter.com/rN89IXZ4MB", "expanded_url": "https://twitter.com/elshenawi4/status/1343442688939585536/photo/1", "type": "photo", "sizes": {"thumb": {"w": 150, "h": 150, "resize": "crop"}, "small": {"w": 384, "h": 200, "resize": "fit"}, "medium": {"w": 384, "h": 200, "resize": "fit"}, "large": {"w": 384, "h": 200, "resize": "fit"}}}]}, "source": "<a href=\"http://twitter.com/download/android\" rel=\"nofollow\">Twitter for Android</a>", "in_reply_to_status_id": 100001, "geo": null, "coordinates": null, "place": null, "contributors": null, "is_quote_status": false, "retweet_count": 0, "favorite_count": 1, "favorited": false, "retweeted": false, "possibly_sensitive": false, "lang": "ar"}, {"created_at": "Mon Sep 21 17:13:21 +0000 2020", "id": 1100848, "full_text": "\u0625\u0646\u064a \u0627\u0631\u064a \u0634\u062c\u0631\u0627 \u064a\u0633\u064a\u0631", "truncated": false, "display_text_range": [0, 17], "entities": {"hashtags": [], "symbols": [], "user_mentions": [], "urls": []}, "source": "<a href=\"http://twitter.com/download/android\" rel=\"nofollow\">Twitter for Android</a>", "in_reply_to_status_id": 100001, "geo": null, "coordinates": null, "place": null, "contributors": null, "is_quote_status": false, "retweet_count": 0, "favorite_count": 0, "favorited": false, "retweeted": false, "lang": "ar"}, {"created_at": "Mon Jun 08 08:24:24 +0000 2020", "id": 1100849, "full_text": "\u0643\u0644 \u0627\u0644\u0644\u0648\u0628\u064a\u0647\u0627\u062a \u062a\u0633\u0639\u064a \u062d\u062b\u064a\u062b\u0629 \u0644\u0632\u0631\u0639 \u0627\u0644\u0623\u0644\u063a\u0627\u0645 \u0644\u0645\u0648\u0627\u0637\u0646 \u064a\u062d\u0644\u0645 \u0628\u0627\u0644\u062d\u0631\u064a\u0647 \u0648\u062f\u0648\u0644\u0647 \u0627\u0644\u0642\u0627\u0646\u0648\u0646", "truncated": false, "display_text_range": [0, 70], "entities": {"hashtags": [], "symbols": [], "user_mentions": [], "urls": []}, "source": "<a href=\"http://twitter.com/download/android\" rel=\"nofollow\">Twitter for Android</a>", "in_reply_to_status_id": 100001, "geo": null, "coordinates": null, "place": null, "contributors": null, "is_quote_status": false, "retweet_count": 0, "favorite_count": 0, "favorited": false, "retweeted": false, "lang": "ar"}, {"created_at": "Thu May 14 13:44:08 +0000 2020", "id": 1100850, "full_text": "\u0644\u0644\u062a\u0639\u0644\u064a\u0645 \u0645\u0627\u0641\u064a\u0627 \u0648\u0639\u0635\u0627\u0628\u0627\u062a \u062c\u0639\u0644\u0648\u0627 \u0644\u0647 \u0645\u062f\u0627\u0631\u0633 \u062e\u0627\u0635\u0647 \u0648\u0645\u0637\u0627\u0628\u0639 \u0643\u062a\u0627\u0628 \u062e\u0627\u0635\u0647 \u0648\u062d\u062a\u064a \u0627\u0644\u0645\u0639\u0644\u0645 \u064a\u0639\u0645\u0644 \u0645\u0639\u0647\u0645 \u0628\u0627\u0644\u0627\u0628\u062a\u0632\u0627\u0632 \n\u0644\u0644\u0639\u0644\u0627\u062c \u0645\u0627\u0641\u064a\u0627 \u0648\u0639\u0635\u0627\u0628\u0627\u062a \u062c\u0639\u0644\u0648\u0627 \u0644\u0647 \u0645\u0633\u062a\u0634\u0641\u064a\u0627\u062a \u062e\u0627\u0635\u0647 \u0648\u0634\u0631\u0643\u0627\u062a \u0627\u0648\u062f\u064a\u0647 \u062e\u0627\u0635\u0647 \u0648\u062d\u062a\u064a \u0627\u0644\u0623\u0637\u0628\u0627\u0621 \u064a\u0639\u0645\u0644\u0648\u0646 \u0641\u064a \u0627\u0644\u062e\u0627\u0635 \u0628\u0627\u0644\u0627\u0628\u062a\u0632\u0627\u0632\n\u0641\u0647\u0645\u062a\u0648\u0627 \u0627\u0644\u0631\u0635\u0647", "truncated": false, "display_text_range": [0, 205], "entities": {"hashtags": [], "symbols": [], "user_mentions": [], "urls": []}, "source": "<a href=\"http://twitter.com/download/android\" rel=\"nofollow\">Twitter for Android</a>", "in_reply_to_status_id": 100001, "geo": null, "coordinates": null, "place": null, "contributors": null, "is_quote_status": false, "retweet_count": 0, "favorite_count": 0, "favorited": false, "retweeted": false, "lang": "ar"}, {"created_at": "Fri Apr 03 09:50:54 +0000 2020", "id": 1100851, "full_text": "\u0639\u0634\u0627\u0646\u0643 \u064a\u0627 \u0633\u0648\u062f\u0627\u0646 ,, \u062a\u0645 \u0627\u0644\u062a\u0628\u0631\u0639 \u0628\u0646\u062c\u0627\u062d. \u0634\u0643\u0631\u0627", "truncated": false, "display_text_range": [0, 39], "entities": {"hashtags": [], "symbols": [], "user_mentions": [], "urls": []}, "source": "<a href=\"http://twitter.com/download/android\" rel=\"nofollow\">Twitter for Android</a>", "in_reply_to_status_id": 100001, "geo": null, "coordinates": null, "place": null, "contributors": null, "is_quote_status": false, "retweet_count": 0, "favorite_count": 0, "favorited": false, "retweeted": false, "lang": "ar"}, {"created_at": "Wed Feb 12 07:02:15 +0000 2020", "id": 1100852, "full_text": "\u0627\u064a\u062f \u0627\u0644\u0639\u0633\u0643\u0631 \u0645\u0623\u062c\u0648\u0631\u0647 \u064a\u0627 \u0646\u0648\u0631\u0627\n\u0627\u0644\u0627\u0632\u0645\u0647 \u0645\u0627 \u0627\u0632\u0645\u0647 \u0631\u063a\u064a\u0641 \u0627\u0644\u0627\u0632\u0645\u0647\n\u0634\u0639\u0628 \u0631\u0627\u0643\u0639 \u0628\u064a\u062d\u0627\u0648\u0644 \u064a\u0642\u064a\u0641", "truncated": false, "display_text_range": [0, 73], "entities": {"hashtags": [], "symbols": [], "user_mentions": [], "urls": []}, "source": "<a href=\"http://twitter.com/download/android\" rel=\"nofollow\">Twitter for Android</a>", "in_reply_to_status_id": 100001, "geo": null, "coordinates": null, "place": null, "contributors": null, "is_quote_status": false, "retweet_count": 0, "favorite_count": 1, "favorited": false, "retweeted": false, "lang": "ar"}, {"created_at": "Sun Sep 15 09:22:02 +0000 2019", "id": 1100853, "full_text": "\u062a\u0631\u062a\u064a\u0628 \u0627\u0644\u0628\u064a\u062a \u0642\u0628\u0644 \u0627\u0633\u062a\u0642\u0628\u0627\u0644 \u0627\u0644\u0636\u064a\u0648\u0641 \u064a\u0627 \u062d\u0645\u062f\u0648\u0643\n \u0648\u0648\u0632\u064a\u0631 \u0627\u0644\u0645\u0627\u0644\u064a\u0647 \u062f\u0627 \u0644\u0648 \u0645\u0627 \u0646\u0638\u0641 \u063a\u0631\u0641\u062a\u0648 (\u0627\u0644\u0648\u0632\u0627\u0631\u0647)\u0645\u0627 \u0639\u0646\u062f\u0646\u0627 \u0644\u064a\u0647\u0648 \u0647\u0644\u0644\u0647", "truncated": false, "display_text_range": [0, 101], "entities": {"hashtags": [], "symbols": [], "user_mentions": [], "urls": []}, "source": "<a href=\"http://twitter.com/download/android\" rel=\"nofollow\">Twitter for Android</a>", "in_reply_to_status_id": 100001, "geo": {"type": "Point", "coordinates": [15.6475831, 32.423967]}, "coordinates": {"type": "Point", "coordinates": [32.423967, 15.6475831]}, "place": {"id": "0e5a1aeadf14d000", "url": "https://api.twitter.com/1.1/geo/id/0e5a1aeadf14d000.json", "place_type": "city", "name": "Omdurman", "full_name": "Omdurman, Sudan", "country_code": "SD", "country": "Sudan", "contained_within": [], "bounding_box": {"type": "Polygon", "coordinates": [[[32.3785257, 15.5157108], [32.5349603, 15.5157108], [32.5349603, 15.7704474], [32.3785257, 15.7704474]]]}, "attributes": {}}, "contributors": null, "is_quote_status": false, "retweet_count": 0, "favorite_count": 0, "favorited": false, "retweeted": false, "lang": "ar"}, {"created_at": "Wed Aug 28 10:31:58 +0000 2019", "id": 1100854, "full_text": "\u0648\u0627\u0644\u0644\u0647 \u0627\u0644\u0630\u064a \u062e\u0644\u0642 \u0627\u0644\u0633\u0645\u0627\u0621 \u0628\u0644\u0627 \u0639\u0645\u062f \u0625\u0646 \u0644\u0645 \u062a\u0632\u062c\u0648 \u0628\u0627\u0644\u0643\u064a\u0632\u0627\u0646 \u0641\u064a \u0627\u0644\u0632\u0646\u0627\u0632\u064a\u0646 \u0648\u062a\u0632\u064a\u063a\u0648\u0647\u0645 \u0627\u0644\u0645 \u0628\u0623\u0644\u0645 \u0648\u062f\u0645 \u0628\u062f\u0645 \u0623\u0643\u0628\u0631 \u0644\u0646 \u062a\u0646\u0627\u0644\u0648\u0627 \u0645\u0627 \u062a\u0635\u0628\u0648\u0646 \u0625\u0644\u064a\u0647 \n#\u0644\u0627 \u0644\u062f\u0641\u0646 \u0627\u0644\u0631\u0624\u0648\u0633", "truncated": false, "display_text_range": [0, 133], "entities": {"hashtags": [{"text": "\u0644\u0627", "indices": [118, 121]}], "symbols": [], "user_mentions": [], "urls": []}, "source": "<a href=\"http://twitter.com/download/android\" rel=\"nofollow\">Twitter for Android</a>", "in_reply_to_status_id": 100001, "geo": null, "coordinates": null, "place": null, "contributors": null, "is_quote_status": false, "retweet_count": 0, "favorite_count": 0, "favorited": false, "retweeted": false, "lang": "ar"}, {"created_at": "Tue Aug 27 09:35:31 +0000 2019", "id": 1100855, "full_text": "\u0645\u0627 \u0641\u064a \u062f\u0648\u0644\u0627\u0631 \u0627\u0644\u0627 \u062a\u062d\u0627\u0643\u0645\u0648 \u0627\u0644\u0643\u064a\u0632\u0627\u0646", "truncated": false, "display_text_range": [0, 30], "entities": {"hashtags": [], "symbols": [], "user_mentions": [], "urls": []}, "source": "<a href=\"http://twitter.com/download/android\" rel=\"nofollow\">Twitter for Android</a>", "in_reply_to_status_id": 100001, "geo": null, "coordinates": null, "place": null, "contributors": null, "is_quote_status": false, "retweet_count": 0, "favorite_count": 0, "favorited": false, "retweeted": false, "lang": "ar"}, {"created_at": "Sun Aug 04 18:12:21 +0000 2019", "id": 1100856, "full_text": "\u0627\u0644\u0630\u0626\u0627\u0628 \u062a\u062a\u062d\u0627\u0644\u0641 \u0639\u0646\u062f \u0627\u0644\u062c\u0648\u0639 \u0648\u0627\u0644\u0627\u062d\u0633\u0627\u0633 \u0628\u0627\u0644\u062e\u0637\u0631\n\u0648\u0627\u0644\u062d\u0631\u0628 \u0644\u0645 \u062a\u0636\u0639 \u0623\u0648\u0632\u0627\u0631\u0647\u0627 \u0628\u0639\u062f\n\u0648\u0637\u0631\u064a\u0642 \u0627\u0644\u062b\u0648\u0631\u0647 \u0645\u0645\u062a\u062f", "truncated": false, "display_text_range": [0, 83], "entities": {"hashtags": [], "symbols": [], "user_mentions": [], "urls": []}, "source": "<a href=\"http://twitter.com/download/android\" rel=\"nofollow\">Twitter for Android</a>", "in_reply_to_status_id": 100001, "geo": null, "coordinates": null, "place": null, "contributors": null, "is_quote_status": false, "retweet_count": 0, "favorite_count": 0, "favorited": false, "retweeted": false, "lang": "ar"}, {"created_at": "Fri Aug 02 19:10:28 +0000 2019", "id": 1100857, "full_text": "\u0645\u0633\u0639\u0648\u0644\u064a\u0646 \u0645\u0646 \u0627\u0644\u062e\u064a\u0631 \n\u0648\u064a\u0646 \u0628\u062a\u0627\u0639 \u0627\u0644\u0645\u0644\u0643\u064a\u0647 \u0627\u0644\u0641\u0643\u0631\u064a\u0647 \u062f\u0627\u0643 \n\u0648\u0647\u0645\u0646\u0647 \u062c\u062f", "truncated": false, "display_text_range": [0, 56], "entities": {"hashtags": [], "symbols": [], "user_mentions": [], "urls": []}, "source": "<a href=\"http://twitter.com/download/android\" rel=\"nofollow\">Twitter for Android</a>", "in_reply_to_status_id": 100001, "geo": null, "coordinates": null, "place": null, "contributors": null, "is_quote_status": false, "retweet_count": 0, "favorite_count": 0, "favorited": false, "retweeted": false, "lang": "ar"}, {"created_at": "Wed Jul 31 10:56:45 +0000 2019", "id": 1100858, "full_text": "\u0627\u062c\u0645\u0644 \u0645\u0627 \u0631\u0623\u062a \u0639\u064a\u0646\u064a\n\u0641\u064a \u0645\u0633\u064a\u0631\u0647 \u064a\u0648\u0645 \u0623\u0645\u0633 \u0663\u0660/\u0667/\u0662\u0660\u0661\u0669 \n\u0637\u0644\u0627\u0628 \u064a\u0634\u0643\u0644\u0648\u0646 \u0637\u0648\u0642\u0627 \u0644\u0645\u0633\u0627\u0631 \u0639\u0628\u0648\u0631\u0627\u0644\u0637\u0627\u0644\u0628\u0627\u062a \u0644\u062d\u0645\u0627\u064a\u062a\u0647\u0646 \n#\u0645\u0646\u0643\u0645 \u0646\u062a\u0639\u0644\u0645 \u0623\u0628\u0646\u0627\u0626\u0646\u0627 https://t.co/O3JMTynYag", "truncated": false, "display_text_range": [0, 110], "entities": {"hashtags": [{"text": "\u0645\u0646\u0643\u0645", "indices": [91, 96]}], "symbols": [], "user_mentions": [], "urls": [], "media": [{"id": 1156519046298394624, "id_str": "1156519046298394624", "indices": [111, 134], "media_url": "http://pbs.twimg.com/media/EAzH8fKW4AADp3S.jpg", "media_url_https": "https://pbs.twimg.com/media/EAzH8fKW4AADp3S.jpg", "url": "https://t.co/O3JMTynYag", "display_url": "pic.twitter.com/O3JMTynYag", "expanded_url": "https://twitter.com/elshenawi4/status/1156519057505554432/photo/1", "type": "photo", "sizes": {"thumb": {"w": 150, "h": 150, "resize": "crop"}, "medium": {"w": 712, "h": 534, "resize": "fit"}, "small": {"w": 680, "h": 510, "resize": "fit"}, "large": {"w": 712, "h": 534, "resize": "fit"}}}]}, "extended_entities": {"media": [{"id": 1156519046298394624, "id_str": "1156519046298394624", "indices": [111, 134], "media_url": "http://pbs.twimg.com/media/EAzH8fKW4AADp3S.jpg", "media_url_https": "https://pbs.twimg.com/media/EAzH8fKW4AADp3S.jpg", "url": "https://t.co/O3JMTynYag", "display_url": "pic.twitter.com/O3JMTynYag", "expanded_url": "https://twitter.com/elshenawi4/status/1156519057505554432/photo/1", "type": "photo", "sizes": {"thumb": {"w": 150, "h": 150, "resize": "crop"}, "medium": {"w": 712, "h": 534, "resize": "fit"}, "small": {"w": 680, "h": 510, "resize": "fit"}, "large": {"w": 712, "h": 534, "resize": "fit"}}}]}, "source": "<a href=\"http://twitter.com/download/android\" rel=\"nofollow\">Twitter for Android</a>", "in_reply_to_status_id": 100001, "geo": null, "coordinates": null, "place": null, "contributors": null, "is_quote_status": false, "retweet_count": 0, "favorite_count": 1, "favorited": false, "retweeted": false, "possibly_sensitive": false, "lang": "ar"}, {"created_at": "Tue Jul 30 07:07:47 +0000 2019", "id": 1100859, "full_text": "\u0627\u0644\u0648\u062d\u0634 \u064a\u0642\u062a\u0644 \u062b\u0627\u0626\u0631\u0627\u064b *** \u0648\u0627\u0644\u0623\u0631\u0636 \u062a\u0646\u0628\u062a \u0623\u0644\u0641 \u062b\u0627\u0626\u0631\u00a0\n\u064a\u0627 \u0643\u0628\u0631\u064a\u0627\u0621 \u0627\u0644\u062c\u0631\u062d *** \u0644\u0648 \u0645\u062a\u0646\u0627 \u0644\u062d\u0627\u0631\u0628\u062a \u0627\u0644\u0645\u0642\u0627\u0628\u0631", "truncated": false, "display_text_range": [0, 86], "entities": {"hashtags": [], "symbols": [], "user_mentions": [], "urls": []}, "source": "<a href=\"http://twitter.com/download/android\" rel=\"nofollow\">Twitter for Android</a>", "in_reply_to_status_id": 100001, "geo": null, "coordinates": null, "place": null, "contributors": null, "is_quote_status": false, "retweet_count": 0, "favorite_count": 1, "favorited": false, "retweeted": false, "lang": "ar"}, {"created_at": "Mon Jul 29 06:41:19 +0000 2019", "id": 1100860, "full_text": "\u0627\u0644\u0644\u0647\u0645 \u0627\u0644\u0641 \u0628\u064a\u0646 \u0642\u0644\u0648\u0628 \u0627\u0644\u0633\u0648\u062f\u0627\u0646\u064a\u064a\u0646\n\u0648\u062d\u0646\u0646 \u0642\u0644\u0648\u0628\u0647\u0645 \u0639\u0644\u064a \u0628\u0639\u0636", "truncated": false, "display_text_range": [0, 49], "entities": {"hashtags": [], "symbols": [], "user_mentions": [], "urls": []}, "source": "<a href=\"http://twitter.com/download/android\" rel=\"nofollow\">Twitter for Android</a>", "in_reply_to_status_id": 100001, "geo": null, "coordinates": null, "place": null, "contributors": null, "is_quote_status": false, "retweet_count": 0, "favorite_count": 0, "favorited": false, "retweeted": false, "lang": "ar"}, {"created_at": "Fri Jul 26 19:09:55 +0000 2019", "id": 1100861, "full_text": "\u0627\u0644\u062d\u0644\u064a\u0641 \u0627\u0644\u0627\u0633\u062a\u0631\u0627\u062a\u064a\u062c\u064a \u0644\u0644\u0627\u062e\u0648\u0627\u0646 \u0644\u0627 \u062a\u0647\u0645\u0644\u0648\u0647\n\u0633\u064a\u0638\u0647\u0631 \u0641\u064a \u0646\u0647\u0627\u064a\u0647 \u0627\u0644\u0645\u0634\u0647\u062f", "truncated": false, "display_text_range": [0, 58], "entities": {"hashtags": [], "symbols": [], "user_mentions": [], "urls": []}, "source": "<a href=\"http://twitter.com/download/android\" rel=\"nofollow\">Twitter for Android</a>", "in_reply_to_status_id": 100001, "geo": null, "coordinates": null, "place": null, "contributors": null, "is_quote_status": false, "retweet_count": 0, "favorite_count": 0, "favorited": false, "retweeted": false, "lang": "ar"}, {"created_at": "Wed Jul 24 20:06:34 +0000 2019", "id": 1100862, "full_text": "\u0627\u0644\u062e\u0627\u0644 \u0627\u0644\u0633\u0641\u064a\u0647 \u062c\u0648\u0647 \u0627\u0644\u062c\u0627\u0643 \n\u0648\u0633\u062e \u0648\u0639\u0646\u0637\u0632\u0647", "truncated": false, "display_text_range": [0, 34], "entities": {"hashtags": [], "symbols": [], "user_mentions": [], "urls": []}, "source": "<a href=\"http://twitter.com/download/android\" rel=\"nofollow\">Twitter for Android</a>", "in_reply_to_status_id": 100001, "geo": null, "coordinates": null, "place": null, "contributors": null, "is_quote_status": false, "retweet_count": 0, "favorite_count": 0, "favorited": false, "retweeted": false, "lang": "ar"}, {"created_at": "Wed Jul 24 20:02:24 +0000 2019", "id": 1100863, "full_text": "\u062d\u0634\u0631\u0627\u062a \u0627\u0644\u062e\u0631\u064a\u0641 \u0628\u062a\u0637\u0644\u0639 \u0641\u064a \u0639\u064a\u0646\u0647 \u0627\u0633\u0645\u0647\u0627 \u0627\u0644\u0646\u062a\u0631\u0647 \n\u0639\u0644\u064a \u0648\u0632\u0646 \u062a\u0641\u0644\u062d\u0648\u0646 \u0628\u0633 \n\u0625\u062b\u064a\u0648\u0628\u064a\u0627 \u0627\u0644\u0645\u0631\u0651\u0647 \u062f\u064a \u0641\u064a\u0647\u0627 \u0627\u0644\u062d\u0631\u0643\u0627\u062a \u0627\u0644\u0645\u0633\u0644\u062d\u0647\n#\u062a\u0641\u0647\u0645  \u0645\u0627 \u062a\u0641\u0647\u0645 \u062f\u064a \u0645\u0634\u0643\u0644\u062a\u0643", "truncated": false, "display_text_range": [0, 123], "entities": {"hashtags": [{"text": "\u062a\u0641\u0647\u0645", "indices": [99, 104]}], "symbols": [], "user_mentions": [], "urls": []}, "source": "<a href=\"http://twitter.com/download/android\" rel=\"nofollow\">Twitter for Android</a>", "in_reply_to_status_id": 100001, "geo": null, "coordinates": null, "place": null, "contributors": null, "is_quote_status": false, "retweet_count": 0, "favorite_count": 0, "favorited": false, "retweeted": false, "lang": "ar"}, {"created_at": "Mon Jul 15 08:41:23 +0000 2019", "id": 1100864, "full_text": "\u0627\u0644\u062a\u0631\u0627\u062c\u0639 \u0645\u0646 \u0645\u0646\u062a\u0635\u0641 \u0637\u0631\u064a\u0642 \u0627\u0644\u062b\u0648\u0631\u0647 \u064a\u062c\u0639\u0644\u0643 \u062a\u062d\u0646 \u0644\u0632\u0645\u0646 \u0627\u0644\u0645\u062e\u0644\u0648\u0639 \u0627\u0644\u0628\u0634\u064a\u0631 \n\u0644\u0627\u0632\u0645 \u062a\u0646\u062a\u0635\u0631 \u0627\u0644\u062b\u0648\u0631\u0647 \u0644\u064a\u0633\u062a\u062d\u064a \u0643\u0644 \u0639\u0627\u0637\u0644 \u0643\u0648\u0632", "truncated": false, "display_text_range": [0, 96], "entities": {"hashtags": [], "symbols": [], "user_mentions": [], "urls": []}, "source": "<a href=\"http://twitter.com/download/android\" rel=\"nofollow\">Twitter for Android</a>", "in_reply_to_status_id": 100001, "geo": null, "coordinates": null, "place": null, "contributors": null, "is_quote_status": false, "retweet_count": 0, "favorite_count": 0, "favorited": false, "retweeted": false, "lang": "ar"}, {"created_at": "Mon Jul 15 08:18:26 +0000 2019", "id": 1100865, "full_text": "\u0627\u0644\u0644\u0647 \u064a\u0643\u0636\u0628 \u0627\u0644\u0634\u064a\u0646\u0647 \n\u0639\u0644\u064a \u0642\u0648\u0644 \u062d\u0628\u0648\u0628\u062a\u064a \u0627\u0644\u0644\u0647 \u064a\u062f\u064a\u0647\u0627 \u0627\u0644\u0635\u062d\u0647 \u0648\u0627\u0644\u0639\u0627\u0641\u064a\u0647", "truncated": false, "display_text_range": [0, 58], "entities": {"hashtags": [], "symbols": [], "user_mentions": [], "urls": []}, "source": "<a href=\"http://twitter.com/download/android\" rel=\"nofollow\">Twitter for Android</a>", "in_reply_to_status_id": 100001, "geo": null, "coordinates": null, "place": null, "contributors": null, "is_quote_status": false, "retweet_count": 0, "favorite_count": 0, "favorited": false, "retweeted": false, "lang": "ar"}, {"created_at": "Thu Jul 11 18:42:28 +0000 2019", "id": 1100866, "full_text": "\u0644\u064a\u0633 \u0647\u0646\u0627\u0643 \u0645\u0627 \u064a\u062f\u0639\u0648 \u0644\u0644\u0641\u0631\u062d \n\u0645\u0627 \u064a\u0631\u0636\u064a \u0627\u0645 \u0627\u0644\u0634\u0647\u064a\u062f \u064a\u0631\u0636\u064a\u0646\u0627 \n#\u0641\u0633\u0631\u0648\u0647\u0627 \u0643\u0644 \u062d\u0633\u0628 \u0641\u0647\u0645\u0647", "truncated": false, "display_text_range": [0, 69], "entities": {"hashtags": [{"text": "\u0641\u0633\u0631\u0648\u0647\u0627", "indices": [50, 57]}], "symbols": [], "user_mentions": [], "urls": []}, "source": "<a href=\"http://twitter.com/download/android\" rel=\"nofollow\">Twitter for Android</a>", "in_reply_to_status_id": 100001, "geo": null, "coordinates": null, "place": null, "contributors": null, "is_quote_status": false, "retweet_count": 0, "favorite_count": 0, "favorited": false, "retweeted": false, "lang": "ar"}, {"created_at": "Thu May 16 09:38:58 +0000 2019", "id": 1100867, "full_text": "\u0639\u0644\u064a \u0639\u062b\u0645\u0627\u0646 \u0642\u0628\u062d \u0627\u0644\u0644\u0647 \u0648\u062c\u0647 \u0644\u0645\u0627 \u0642\u0627\u0644 \u062f\u064a\u0644 \u0636\u0628\u0627\u0637\u0646\u0627 \u0648\u0645\u0627 \u0628\u0633\u0644\u0645\u0648\u0643\u0645 \u0644\u064a\u0647\u0627 \u0643\u0627\u0646 \u0648\u0627\u062b\u0642 \u062b\u0642\u0647 \u0627\u0644\u0645\u0627\u0644\u0643 \u0644\u0645\u0644\u0641\u0627\u062a \u0641\u0633\u0627\u062f\u0647\u0645 \u0641\u064a \u062c\u064a\u0628\u0647  \n#\u0627\u0644\u0641\u0633\u0627\u062f \u064a\u0637\u0627\u0637\u0626 \u0627\u0644\u0631\u0624\u0633", "truncated": false, "display_text_range": [0, 122], "entities": {"hashtags": [{"text": "\u0627\u0644\u0641\u0633\u0627\u062f", "indices": [103, 110]}], "symbols": [], "user_mentions": [], "urls": []}, "source": "<a href=\"http://twitter.com/download/android\" rel=\"nofollow\">Twitter for Android</a>", "in_reply_to_status_id": 100001, "geo": null, "coordinates": null, "place": null, "contributors": null, "is_quote_status": false, "retweet_count": 0, "favorite_count": 0, "favorited": false, "retweeted": false, "lang": "ar"}, {"created_at": "Thu May 16 09:08:23 +0000 2019", "id": 1100868, "full_text": "\u0627\u0644\u0645\u0627\u0628\u064a\u0643 \u0641\u064a \u0627\u0644\u0638\u0644\u0627\u0645 \u0628\u064a\u062d\u062f\u0631 \u0644\u064a\u0643 \n\u0627\u0639\u0646\u064a\u0643 \u064a\u0627 \u0644\u0627\u0628\u0633 \u0628\u0648\u062a \u0627\u0644\u062f\u0645", "truncated": false, "display_text_range": [0, 51], "entities": {"hashtags": [], "symbols": [], "user_mentions": [], "urls": []}, "source": "<a href=\"http://twitter.com/download/android\" rel=\"nofollow\">Twitter for Android</a>", "in_reply_to_status_id": 100001, "geo": null, "coordinates": null, "place": null, "contributors": null, "is_quote_status": false, "retweet_count": 0, "favorite_count": 0, "favorited": false, "retweeted": false, "lang": "ar"}, {"created_at": "Sun Apr 28 08:33:58 +0000 2019", "id": 1100869, "full_text": "\u0645\u0646 \u0623\u0633\u0628\u0627\u0628 \u0641\u0634\u0644\u0646\u0627 \n\u0627\u0639\u062a\u0632\u0627\u0631 \u0648\u0627\u0639\u062a\u0632\u0627\u0644 \u0643\u0641\u0627\u0621\u0627\u062a\u0646\u0627 \u0644\u0642\u0628\u0648\u0644 \u0627\u0644\u062a\u0643\u0644\u064a\u0641 \u0648\u0627\u0644\u0645\u0633\u0627\u0639\u062f\u0647 \u0641\u064a \u0627\u0644\u0646\u0647\u0648\u0636", "truncated": false, "display_text_range": [0, 73], "entities": {"hashtags": [], "symbols": [], "user_mentions": [], "urls": []}, "source": "<a href=\"http://twitter.com/download/android\" rel=\"nofollow\">Twitter for Android</a>", "in_reply_to_status_id": 100001, "geo": null, "coordinates": null, "place": null, "contributors": null, "is_quote_status": false, "retweet_count": 0, "favorite_count": 0, "favorited": false, "retweeted": false, "lang": "ar"}, {"created_at": "Thu Apr 25 09:01:38 +0000 2019", "id": 1100870, "full_text": "\u062d\u0646\u0628\u0646\u064a\u0647\u0648 \u0627\u0644\u0628\u0646\u062d\u0644\u0645 \u0628\u064a\u0647\u0648 \u064a\u0648\u0645\u0627\u062a\u064a\n\u0648\u0637\u0646 \u0634\u0627\u0645\u062e", "truncated": false, "display_text_range": [0, 36], "entities": {"hashtags": [], "symbols": [], "user_mentions": [], "urls": []}, "source": "<a href=\"https://mobile.twitter.com\" rel=\"nofollow\">Twitter Web App</a>", "in_reply_to_status_id": 100001, "geo": null, "coordinates": null, "place": null, "contributors": null, "is_quote_status": false, "retweet_count": 0, "favorite_count": 0, "favorited": false, "retweeted": false, "lang": "ar"}], "user": {"id": 1100871, "location": "Omdurman", "description": "\u200f\u0627\u0643\u0631\u0647 \u062d\u064a\u0627\u0647 \u0627\u0644\u0645\u0646\u0627\u0641\u0642\u064a\u0646", "entities": {"description": {"urls": []}}, "protected": false, "followers_count": 12, "friends_count": 92, "listed_count": 0, "created_at": "Wed Apr 24 20:23:33 +0000 2019", "favourites_count": 91, "utc_offset": null, "time_zone": null, "geo_enabled": true, "verified": false, "statuses_count": 57, "lang": null, "contributors_enabled": false, "is_translator": false, "is_translation_enabled": false, "profile_background_color": "F5F8FA", "profile_background_tile": false, "profile_link_color": "1DA1F2", "profile_sidebar_border_color": 100382, "profile_sidebar_fill_color": 100383, "profile_text_color": "333333", "profile_use_background_image": true, "has_extended_profile": true, "default_profile": true, "default_profile_image": false, "notifications": null, "translator_type": "none", "withheld_in_countries": []}, "label": "35-49"}