{"tweets": [{"created_at": "Tue Nov 02 12:23:46 +0000 2021", "id": 2061886, "full_text": "https://t.co/xB9sY4foPb", "truncated": false, "display_text_range": [0, 0], "entities": {"hashtags": [], "symbols": [], "user_mentions": [], "urls": [], "media": [{"id": 1455510945590038535, "id_str": "1455510945590038535", "indices": [0, 23], "media_url": "http://pbs.twimg.com/media/FDMDfk6WUAcBPH2.jpg", "media_url_https": "https://pbs.twimg.com/media/FDMDfk6WUAcBPH2.jpg", "url": "https://t.co/xB9sY4foPb", "display_url": "pic.twitter.com/xB9sY4foPb", "expanded_url": "https://twitter.com/8qtBfWYd9AI6QKZ/status/1455510948161204236/photo/1", "type": "photo", "sizes": {"thumb": {"w": 150, "h": 150, "resize": "crop"}, "large": {"w": 720, "h": 720, "resize": "fit"}, "small": {"w": 680, "h": 680, "resize": "fit"}, "medium": {"w": 720, "h": 720, "resize": "fit"}}}]}, "extended_entities": {"media": [{"id": 1455510945590038535, "id_str": "1455510945590038535", "indices": [0, 23], "media_url": "http://pbs.twimg.com/media/FDMDfk6WUAcBPH2.jpg", "media_url_https": "https://pbs.twimg.com/media/FDMDfk6WUAcBPH2.jpg", "url": "https://t.co/xB9sY4foPb", "display_url": "pic.twitter.com/xB9sY4foPb", "expanded_url": "https://twitter.com/8qtBfWYd9AI6QKZ/status/1455510948161204236/photo/1", "type": "photo", "sizes": {"thumb": {"w": 150, "h": 150, "resize": "crop"}, "large": {"w": 720, "h": 720, "resize": "fit"}, "small": {"w": 680, "h": 680, "resize": "fit"}, "medium": {"w": 720, "h": 720, "resize": "fit"}}}]}, "source": "<a href=\"http://twitter.com/download/android\" rel=\"nofollow\">Twitter for Android</a>", "in_reply_to_status_id": 100001, "geo": null, "coordinates": null, "place": null, "contributors": null, "is_quote_status": false, "retweet_count": 0, "favorite_count": 1, "favorited": false, "retweeted": false, "possibly_sensitive": false, "lang": "und"}, {"created_at": "Thu Oct 07 10:19:56 +0000 2021", "id": 2061887, "full_text": "https://t.co/Rl9xGTyEkv", "truncated": false, "display_text_range": [0, 23], "entities": {"hashtags": [], "symbols": [], "user_mentions": [], "urls": [{"url": "https://t.co/Rl9xGTyEkv", "expanded_url": "https://www.facebook.com/100070502206010/posts/137162518643821/?sfnsn=mo", "display_url": "facebook.com/10007050220601\u2026", "indices": [0, 23]}]}, "source": "<a href=\"http://twitter.com/download/android\" rel=\"nofollow\">Twitter for Android</a>", "in_reply_to_status_id": 100001, "geo": null, "coordinates": null, "place": null, "contributors": null, "is_quote_status": false, "retweet_count": 0, "favorite_count": 1, "favorited": false, "retweeted": false, "possibly_sensitive": false, "lang": "und"}, {"created_at": "Mon Oct 04 21:18:06 +0000 2021", "id": 2061888, "full_text": "\u0627\u0630\u0644\u0647\u0645 \u0627\u0644\u0644\u0647 \u0639\u0632 \u0648\u062c\u0644 \n\u0646\u0638\u064a\u0631 \u0627\u0633\u062a\u0647\u0632\u0627\u0626\u0647\u0645 \u0628\u0631\u0633\u0648\u0644 \u0627\u0644\u0644\u0647 \u0635\u0644 \u0627\u0644\u0644\u0647 \u0639\u0644\u064a\u0647 \u0648\u0633\u0644\u0645 https://t.co/nftwyBwZzr", "truncated": false, "display_text_range": [0, 62], "entities": {"hashtags": [], "symbols": [], "user_mentions": [], "urls": [], "media": [{"id": 1445136161631096844, "id_str": "1445136161631096844", "indices": [63, 86], "media_url": "http://pbs.twimg.com/media/FA4nrq4X0AwD8Ru.jpg", "media_url_https": "https://pbs.twimg.com/media/FA4nrq4X0AwD8Ru.jpg", "url": "https://t.co/nftwyBwZzr", "display_url": "pic.twitter.com/nftwyBwZzr", "expanded_url": "https://twitter.com/8qtBfWYd9AI6QKZ/status/1445136169860321280/photo/1", "type": "photo", "sizes": {"thumb": {"w": 150, "h": 150, "resize": "crop"}, "large": {"w": 600, "h": 336, "resize": "fit"}, "small": {"w": 600, "h": 336, "resize": "fit"}, "medium": {"w": 600, "h": 336, "resize": "fit"}}}]}, "extended_entities": {"media": [{"id": 1445136161631096844, "id_str": "1445136161631096844", "indices": [63, 86], "media_url": "http://pbs.twimg.com/media/FA4nrq4X0AwD8Ru.jpg", "media_url_https": "https://pbs.twimg.com/media/FA4nrq4X0AwD8Ru.jpg", "url": "https://t.co/nftwyBwZzr", "display_url": "pic.twitter.com/nftwyBwZzr", "expanded_url": "https://twitter.com/8qtBfWYd9AI6QKZ/status/1445136169860321280/photo/1", "type": "photo", "sizes": {"thumb": {"w": 150, "h": 150, "resize": "crop"}, "large": {"w": 600, "h": 336, "resize": "fit"}, "small": {"w": 600, "h": 336, "resize": "fit"}, "medium": {"w": 600, "h": 336, "resize": "fit"}}}, {"id": 1445136167045898251, "id_str": "1445136167045898251", "indices": [63, 86], "media_url": "http://pbs.twimg.com/media/FA4nr_DXIAs9-Kf.jpg", "media_url_https": "https://pbs.twimg.com/media/FA4nr_DXIAs9-Kf.jpg", "url": "https://t.co/nftwyBwZzr", "display_url": "pic.twitter.com/nftwyBwZzr", "expanded_url": "https://twitter.com/8qtBfWYd9AI6QKZ/status/1445136169860321280/photo/1", "type": "photo", "sizes": {"thumb": {"w": 150, "h": 150, "resize": "crop"}, "large": {"w": 720, "h": 405, "resize": "fit"}, "medium": {"w": 720, "h": 405, "resize": "fit"}, "small": {"w": 680, "h": 383, "resize": "fit"}}}]}, "source": "<a href=\"http://twitter.com/download/android\" rel=\"nofollow\">Twitter for Android</a>", "in_reply_to_status_id": 100001, "geo": null, "coordinates": null, "place": null, "contributors": null, "is_quote_status": false, "retweet_count": 0, "favorite_count": 2, "favorited": false, "retweeted": false, "possibly_sensitive": false, "lang": "ar"}, {"created_at": "Wed Sep 29 22:04:44 +0000 2021", "id": 2061889, "full_text": "https://t.co/D49d9q2vVy", "truncated": false, "display_text_range": [0, 0], "entities": {"hashtags": [], "symbols": [], "user_mentions": [], "urls": [], "media": [{"id": 1443335963820838926, "id_str": "1443335963820838926", "indices": [0, 23], "media_url": "http://pbs.twimg.com/media/FAfCaXcWUA4CygA.jpg", "media_url_https": "https://pbs.twimg.com/media/FAfCaXcWUA4CygA.jpg", "url": "https://t.co/D49d9q2vVy", "display_url": "pic.twitter.com/D49d9q2vVy", "expanded_url": "https://twitter.com/8qtBfWYd9AI6QKZ/status/1443335965968379906/photo/1", "type": "photo", "sizes": {"small": {"w": 481, "h": 680, "resize": "fit"}, "thumb": {"w": 150, "h": 150, "resize": "crop"}, "large": {"w": 720, "h": 1018, "resize": "fit"}, "medium": {"w": 720, "h": 1018, "resize": "fit"}}}]}, "extended_entities": {"media": [{"id": 1443335963820838926, "id_str": "1443335963820838926", "indices": [0, 23], "media_url": "http://pbs.twimg.com/media/FAfCaXcWUA4CygA.jpg", "media_url_https": "https://pbs.twimg.com/media/FAfCaXcWUA4CygA.jpg", "url": "https://t.co/D49d9q2vVy", "display_url": "pic.twitter.com/D49d9q2vVy", "expanded_url": "https://twitter.com/8qtBfWYd9AI6QKZ/status/1443335965968379906/photo/1", "type": "photo", "sizes": {"small": {"w": 481, "h": 680, "resize": "fit"}, "thumb": {"w": 150, "h": 150, "resize": "crop"}, "large": {"w": 720, "h": 1018, "resize": "fit"}, "medium": {"w": 720, "h": 1018, "resize": "fit"}}}]}, "source": "<a href=\"http://twitter.com/download/android\" rel=\"nofollow\">Twitter for Android</a>", "in_reply_to_status_id": 100001, "geo": null, "coordinates": null, "place": null, "contributors": null, "is_quote_status": false, "retweet_count": 0, "favorite_count": 1, "favorited": false, "retweeted": false, "possibly_sensitive": false, "lang": "und"}, {"created_at": "Sun Sep 05 19:31:51 +0000 2021", "id": 2061890, "full_text": "https://t.co/fnCowEEJbd", "truncated": false, "display_text_range": [0, 23], "entities": {"hashtags": [], "symbols": [], "user_mentions": [], "urls": [{"url": "https://t.co/fnCowEEJbd", "expanded_url": "https://m.facebook.com/story.php?story_fbid=714976952172153&id=100009795641808&extid=xCrvmqvDQ4MKs76b&d=t&vh=i", "display_url": "m.facebook.com/story.php?stor\u2026", "indices": [0, 23]}]}, "source": "<a href=\"http://twitter.com/download/android\" rel=\"nofollow\">Twitter for Android</a>", "in_reply_to_status_id": 100001, "geo": null, "coordinates": null, "place": null, "contributors": null, "is_quote_status": false, "retweet_count": 0, "favorite_count": 0, "favorited": false, "retweeted": false, "possibly_sensitive": false, "lang": "und"}, {"created_at": "Sun Sep 05 19:31:47 +0000 2021", "id": 2061891, "full_text": "https://t.co/Ly5Uk3cr2w", "truncated": false, "display_text_range": [0, 23], "entities": {"hashtags": [], "symbols": [], "user_mentions": [], "urls": [{"url": "https://t.co/Ly5Uk3cr2w", "expanded_url": "https://m.facebook.com/story.php?story_fbid=717667828569732&id=100009795641808&extid=wucIccTioHbsa0Eq&d=t&vh=i", "display_url": "m.facebook.com/story.php?stor\u2026", "indices": [0, 23]}]}, "source": "<a href=\"http://twitter.com/download/android\" rel=\"nofollow\">Twitter for Android</a>", "in_reply_to_status_id": 100001, "geo": null, "coordinates": null, "place": null, "contributors": null, "is_quote_status": false, "retweet_count": 0, "favorite_count": 0, "favorited": false, "retweeted": false, "possibly_sensitive": false, "lang": "und"}, {"created_at": "Thu Jul 29 22:08:32 +0000 2021", "id": 2061892, "full_text": "https://t.co/7Pq2Yv6Qcd", "truncated": false, "display_text_range": [0, 0], "entities": {"hashtags": [], "symbols": [], "user_mentions": [], "urls": [], "media": [{"id": 1420868870718513152, "id_str": "1420868870718513152", "indices": [0, 23], "media_url": "http://pbs.twimg.com/media/E7fwtbeWYAA28rN.jpg", "media_url_https": "https://pbs.twimg.com/media/E7fwtbeWYAA28rN.jpg", "url": "https://t.co/7Pq2Yv6Qcd", "display_url": "pic.twitter.com/7Pq2Yv6Qcd", "expanded_url": "https://twitter.com/8qtBfWYd9AI6QKZ/status/1420868873822289920/photo/1", "type": "photo", "sizes": {"medium": {"w": 346, "h": 440, "resize": "fit"}, "thumb": {"w": 150, "h": 150, "resize": "crop"}, "small": {"w": 346, "h": 440, "resize": "fit"}, "large": {"w": 346, "h": 440, "resize": "fit"}}}]}, "extended_entities": {"media": [{"id": 1420868870718513152, "id_str": "1420868870718513152", "indices": [0, 23], "media_url": "http://pbs.twimg.com/media/E7fwtbeWYAA28rN.jpg", "media_url_https": "https://pbs.twimg.com/media/E7fwtbeWYAA28rN.jpg", "url": "https://t.co/7Pq2Yv6Qcd", "display_url": "pic.twitter.com/7Pq2Yv6Qcd", "expanded_url": "https://twitter.com/8qtBfWYd9AI6QKZ/status/1420868873822289920/photo/1", "type": "photo", "sizes": {"medium": {"w": 346, "h": 440, "resize": "fit"}, "thumb": {"w": 150, "h": 150, "resize": "crop"}, "small": {"w": 346, "h": 440, "resize": "fit"}, "large": {"w": 346, "h": 440, "resize": "fit"}}}]}, "source": "<a href=\"http://twitter.com/download/android\" rel=\"nofollow\">Twitter for Android</a>", "in_reply_to_status_id": 100001, "geo": null, "coordinates": null, "place": null, "contributors": null, "is_quote_status": false, "retweet_count": 0, "favorite_count": 0, "favorited": false, "retweeted": false, "possibly_sensitive": false, "lang": "und"}, {"created_at": "Tue Jul 27 02:45:45 +0000 2021", "id": 2061893, "full_text": "https://t.co/kyJSxwgkXV", "truncated": false, "display_text_range": [0, 0], "entities": {"hashtags": [], "symbols": [], "user_mentions": [], "urls": [], "media": [{"id": 1419851462201561091, "id_str": "1419851462201561091", "indices": [0, 23], "media_url": "http://pbs.twimg.com/media/E7RTYdZX0AMEtbg.jpg", "media_url_https": "https://pbs.twimg.com/media/E7RTYdZX0AMEtbg.jpg", "url": "https://t.co/kyJSxwgkXV", "display_url": "pic.twitter.com/kyJSxwgkXV", "expanded_url": "https://twitter.com/8qtBfWYd9AI6QKZ/status/1419851472808857601/photo/1", "type": "photo", "sizes": {"medium": {"w": 974, "h": 1024, "resize": "fit"}, "thumb": {"w": 150, "h": 150, "resize": "crop"}, "small": {"w": 647, "h": 680, "resize": "fit"}, "large": {"w": 974, "h": 1024, "resize": "fit"}}}]}, "extended_entities": {"media": [{"id": 1419851462201561091, "id_str": "1419851462201561091", "indices": [0, 23], "media_url": "http://pbs.twimg.com/media/E7RTYdZX0AMEtbg.jpg", "media_url_https": "https://pbs.twimg.com/media/E7RTYdZX0AMEtbg.jpg", "url": "https://t.co/kyJSxwgkXV", "display_url": "pic.twitter.com/kyJSxwgkXV", "expanded_url": "https://twitter.com/8qtBfWYd9AI6QKZ/status/1419851472808857601/photo/1", "type": "photo", "sizes": {"medium": {"w": 974, "h": 1024, "resize": "fit"}, "thumb": {"w": 150, "h": 150, "resize": "crop"}, "small": {"w": 647, "h": 680, "resize": "fit"}, "large": {"w": 974, "h": 1024, "resize": "fit"}}}]}, "source": "<a href=\"http://twitter.com/download/android\" rel=\"nofollow\">Twitter for Android</a>", "in_reply_to_status_id": 100001, "geo": null, "coordinates": null, "place": null, "contributors": null, "is_quote_status": false, "retweet_count": 0, "favorite_count": 0, "favorited": false, "retweeted": false, "possibly_sensitive": false, "lang": "und"}, {"created_at": "Sun Apr 18 18:55:32 +0000 2021", "id": 2061894, "full_text": "\u0627\u0644\u0633\u0627\u062f\u0629 \u0627\u0644\u0623\u0641\u0627\u0636\u0644 \u0648\u0632\u0627\u0631\u0629 \u0627\u0644\u062f\u0627\u062e\u0644\u064a\u0629  \n\u0627\u0644\u0633\u0644\u0627\u0645 \u0639\u0644\u064a\u0643\u0645 \n\u0627\u0631\u062c\u0648 \u0627\u0644\u0627\u0647\u062a\u0645\u0627\u0645 \u0628\u0637\u0631\u064a\u0642 \u0627\u0644\u0645\u0637\u0627\u0631 \n\u0645\u0646 \u062c\u0632\u064a\u0631\u0629 \u0628\u0627\u0628 \u0627\u0644\u0639\u0632\u064a\u0632\u064a\u0629 \u0625\u0644\u0649 \u0643\u0648\u0628\u0631\u0649 \u0627\u0644\u0645\u0637\u0627\u0631 \n\u0627\u0633\u0645\u0647\u0627 \u0637\u0631\u064a\u0642 \u0627\u0644\u0645\u0648\u062a \u0644\u0644\u0627\u0633\u0641 \u0627\u0644\u0634\u062f\u064a\u062f \u0645\u0646 \u0643\u062b\u0631\u0629 \u062d\u0648\u0627\u062f\u062b \u0627\u0644\u0645\u0631\u0648\u0631 \u0628\u0647\u0627 \n\u0627\u0631\u062c\u0648 \u0627\u0644\u0627\u0647\u062a\u0645\u0627\u0645 \u0628\u0627\u0644\u062c\u0633\u0631 \u0627\u0644\u062d\u062f\u064a\u062f\u0649 \n\u063a\u064a\u0627\u0628 \u062a\u0627\u0645 \u0644\u062f\u0648\u0631\u064a\u0627\u062a \u0634\u0631\u0637\u0629 \u0627\u0644\u0645\u0631\u0648\u0631 \u0648\u0627\u0644\u0646\u062c\u062f\u0629 \u0635\u0628\u0627\u062d\u0627 \u0648\u0644\u064a\u0644\u0627 \n\u0644\u0643\u0645 \u0641\u0627\u0626\u0642 \u0627\u0644\u0627\u062d\u062a\u0631\u0627\u0645 \u0648\u0627\u0644\u062a\u0642\u062f\u064a\u0631", "truncated": false, "display_text_range": [0, 276], "entities": {"hashtags": [], "symbols": [], "user_mentions": [], "urls": []}, "source": "<a href=\"http://twitter.com/download/android\" rel=\"nofollow\">Twitter for Android</a>", "in_reply_to_status_id": 100001, "geo": null, "coordinates": null, "place": null, "contributors": null, "is_quote_status": false, "retweet_count": 0, "favorite_count": 0, "favorited": false, "retweeted": false, "lang": "ar"}, {"created_at": "Tue Dec 22 15:27:29 +0000 2020", "id": 2061895, "full_text": "https://t.co/qZrRvGMcB2", "truncated": false, "display_text_range": [0, 23], "entities": {"hashtags": [], "symbols": [], "user_mentions": [], "urls": [{"url": "https://t.co/qZrRvGMcB2", "expanded_url": "https://m.facebook.com/story.php?story_fbid=1344708802532295&id=100009795641808&sfnsn=mo", "display_url": "m.facebook.com/story.php?stor\u2026", "indices": [0, 23]}]}, "source": "<a href=\"http://twitter.com/download/android\" rel=\"nofollow\">Twitter for Android</a>", "in_reply_to_status_id": 100001, "geo": null, "coordinates": null, "place": null, "contributors": null, "is_quote_status": false, "retweet_count": 0, "favorite_count": 0, "favorited": false, "retweeted": false, "possibly_sensitive": false, "lang": "und"}, {"created_at": "Tue Aug 18 20:58:18 +0000 2020", "id": 2061896, "full_text": "https://t.co/fnCowEEJbd", "truncated": false, "display_text_range": [0, 23], "entities": {"hashtags": [], "symbols": [], "user_mentions": [], "urls": [{"url": "https://t.co/fnCowEEJbd", "expanded_url": "https://m.facebook.com/story.php?story_fbid=714976952172153&id=100009795641808&extid=xCrvmqvDQ4MKs76b&d=t&vh=i", "display_url": "m.facebook.com/story.php?stor\u2026", "indices": [0, 23]}]}, "source": "<a href=\"http://twitter.com/download/android\" rel=\"nofollow\">Twitter for Android</a>", "in_reply_to_status_id": 100001, "geo": null, "coordinates": null, "place": null, "contributors": null, "is_quote_status": false, "retweet_count": 0, "favorite_count": 1, "favorited": false, "retweeted": false, "possibly_sensitive": false, "lang": "und"}, {"created_at": "Tue Aug 18 20:57:46 +0000 2020", "id": 2061897, "full_text": "https://t.co/Ly5Uk3cr2w", "truncated": false, "display_text_range": [0, 23], "entities": {"hashtags": [], "symbols": [], "user_mentions": [], "urls": [{"url": "https://t.co/Ly5Uk3cr2w", "expanded_url": "https://m.facebook.com/story.php?story_fbid=717667828569732&id=100009795641808&extid=wucIccTioHbsa0Eq&d=t&vh=i", "display_url": "m.facebook.com/story.php?stor\u2026", "indices": [0, 23]}]}, "source": "<a href=\"http://twitter.com/download/android\" rel=\"nofollow\">Twitter for Android</a>", "in_reply_to_status_id": 100001, "geo": null, "coordinates": null, "place": null, "contributors": null, "is_quote_status": false, "retweet_count": 0, "favorite_count": 1, "favorited": false, "retweeted": false, "possibly_sensitive": false, "lang": "und"}, {"created_at": "Tue Aug 18 20:54:59 +0000 2020", "id": 2061898, "full_text": "\u0641\u0633\u0627\u062f \u0627\u0644\u0634\u0631\u0643\u0629 \u0627\u0644\u0639\u0627\u0645\u0629 \u0644\u0644\u0643\u0647\u0631\u0628\u0627\u0621 \n\u0645\u0646 \u0623\u062c\u0644 \u062e\u062f\u0645\u0629 \u0627\u0644\u0645\u0641\u0633\u062f\u064a\u0646 https://t.co/eQkzeC2ZVV", "truncated": false, "display_text_range": [0, 49], "entities": {"hashtags": [], "symbols": [], "user_mentions": [], "urls": [], "media": [{"id": 1295826529180688386, "id_str": "1295826529180688386", "indices": [50, 73], "media_url": "http://pbs.twimg.com/media/EfuzXNpXoAI6Q7J.jpg", "media_url_https": "https://pbs.twimg.com/media/EfuzXNpXoAI6Q7J.jpg", "url": "https://t.co/eQkzeC2ZVV", "display_url": "pic.twitter.com/eQkzeC2ZVV", "expanded_url": "https://twitter.com/8qtBfWYd9AI6QKZ/status/1295826551586672642/photo/1", "type": "photo", "sizes": {"medium": {"w": 1200, "h": 677, "resize": "fit"}, "small": {"w": 680, "h": 384, "resize": "fit"}, "thumb": {"w": 150, "h": 150, "resize": "crop"}, "large": {"w": 1984, "h": 1120, "resize": "fit"}}}]}, "extended_entities": {"media": [{"id": 1295826529180688386, "id_str": "1295826529180688386", "indices": [50, 73], "media_url": "http://pbs.twimg.com/media/EfuzXNpXoAI6Q7J.jpg", "media_url_https": "https://pbs.twimg.com/media/EfuzXNpXoAI6Q7J.jpg", "url": "https://t.co/eQkzeC2ZVV", "display_url": "pic.twitter.com/eQkzeC2ZVV", "expanded_url": "https://twitter.com/8qtBfWYd9AI6QKZ/status/1295826551586672642/photo/1", "type": "photo", "sizes": {"medium": {"w": 1200, "h": 677, "resize": "fit"}, "small": {"w": 680, "h": 384, "resize": "fit"}, "thumb": {"w": 150, "h": 150, "resize": "crop"}, "large": {"w": 1984, "h": 1120, "resize": "fit"}}}, {"id": 1295826541100892162, "id_str": "1295826541100892162", "indices": [50, 73], "media_url": "http://pbs.twimg.com/media/EfuzX6DXgAI6q9t.jpg", "media_url_https": "https://pbs.twimg.com/media/EfuzX6DXgAI6q9t.jpg", "url": "https://t.co/eQkzeC2ZVV", "display_url": "pic.twitter.com/eQkzeC2ZVV", "expanded_url": "https://twitter.com/8qtBfWYd9AI6QKZ/status/1295826551586672642/photo/1", "type": "photo", "sizes": {"medium": {"w": 1200, "h": 675, "resize": "fit"}, "thumb": {"w": 150, "h": 150, "resize": "crop"}, "small": {"w": 680, "h": 383, "resize": "fit"}, "large": {"w": 1992, "h": 1121, "resize": "fit"}}}]}, "source": "<a href=\"http://twitter.com/download/android\" rel=\"nofollow\">Twitter for Android</a>", "in_reply_to_status_id": 100001, "geo": null, "coordinates": null, "place": null, "contributors": null, "is_quote_status": false, "retweet_count": 0, "favorite_count": 2, "favorited": false, "retweeted": false, "possibly_sensitive": false, "lang": "ar"}, {"created_at": "Wed Jun 03 20:18:55 +0000 2020", "id": 2061899, "full_text": "\u062d\u0633\u0628\u064a \u0627\u0644\u0644\u0647 \u0648\u0646\u0639\u0645 \u0627\u0644\u0648\u0643\u064a\u0644 \u0641\u0649 \u0627\u0644\u0638\u0627\u0644\u0645 \u0627\u0644\u0645\u0639\u062a\u062f\u0649 \u0628\u0634\u0627\u0631 \u0627\u0644\u0646\u0639\u062c\u0629 \u0648\u0645\u0624\u064a\u062f\u064a\u0647 \nhttps://t.co/1JFIzW5aTo", "truncated": false, "display_text_range": [0, 84], "entities": {"hashtags": [], "symbols": [], "user_mentions": [], "urls": [{"url": "https://t.co/1JFIzW5aTo", "expanded_url": "https://www.facebook.com/Orient.Tv.Net/videos/2623048397936634/?d=t&vh=e", "display_url": "facebook.com/Orient.Tv.Net/\u2026", "indices": [61, 84]}]}, "source": "<a href=\"http://twitter.com/download/android\" rel=\"nofollow\">Twitter for Android</a>", "in_reply_to_status_id": 100001, "geo": null, "coordinates": null, "place": null, "contributors": null, "is_quote_status": false, "retweet_count": 0, "favorite_count": 0, "favorited": false, "retweeted": false, "possibly_sensitive": false, "lang": "ar"}, {"created_at": "Mon Jun 01 00:15:24 +0000 2020", "id": 2061900, "full_text": "\u062d\u0633\u0628\u064a \u0627\u0644\u0644\u0647 \u0648\u0646\u0639\u0645 \u0627\u0644\u0648\u0643\u064a\u0644 \u0641\u0649 \u0627\u0644\u0638\u0627\u0644\u0645 \u0627\u0644\u0645\u0639\u062a\u062f\u0649 \u0628\u0634\u0627\u0631 \u0627\u0644\u0646\u0639\u062c\u0629 \u0648\u0645\u0624\u064a\u062f\u064a\u0647 \nhttps://t.co/1JFIzW5aTo", "truncated": false, "display_text_range": [0, 84], "entities": {"hashtags": [], "symbols": [], "user_mentions": [], "urls": [{"url": "https://t.co/1JFIzW5aTo", "expanded_url": "https://www.facebook.com/Orient.Tv.Net/videos/2623048397936634/?d=t&vh=e", "display_url": "facebook.com/Orient.Tv.Net/\u2026", "indices": [61, 84]}]}, "source": "<a href=\"http://twitter.com/download/android\" rel=\"nofollow\">Twitter for Android</a>", "in_reply_to_status_id": 100001, "geo": null, "coordinates": null, "place": null, "contributors": null, "is_quote_status": false, "retweet_count": 0, "favorite_count": 0, "favorited": false, "retweeted": false, "possibly_sensitive": false, "lang": "ar"}], "user": {"id": 2061901, "location": " \u0637\u0631\u0627\u0628\u0644\u0633 \u0644\u064a\u0628\u064a\u0627", "description": "", "entities": {"description": {"urls": []}}, "protected": false, "followers_count": 31, "friends_count": 83, "listed_count": 0, "created_at": "Thu Jan 16 11:03:32 +0000 2020", "favourites_count": 1524, "utc_offset": null, "time_zone": null, "geo_enabled": true, "verified": false, "statuses_count": 696, "lang": null, "contributors_enabled": false, "is_translator": false, "is_translation_enabled": false, "profile_background_color": "F5F8FA", "profile_background_tile": false, "profile_link_color": "1DA1F2", "profile_sidebar_border_color": 100382, "profile_sidebar_fill_color": 100383, "profile_text_color": "333333", "profile_use_background_image": true, "has_extended_profile": true, "default_profile": true, "default_profile_image": false, "notifications": null, "translator_type": "none", "withheld_in_countries": []}, "label": "50-64"}